vedro_pw/__init__.py
vedro_pw/_async_expect.py
vedro_pw/_capture_mode.py
vedro_pw/_configurable_browser.py
vedro_pw/_pw_browser.py
vedro_pw/_pw_plugin.py
vedro_pw/_runtime_config.py
vedro_pw/_unpack.py
vedro_pw/_utils.py
vedro_pw/async_api.py
vedro_pw/options.py
vedro_pw/py.typed
vedro_pw-0.4.0.dist-info/licenses/LICENSE
vedro_pw-0.4.0.dist-info/METADATA
vedro_pw-0.4.0.dist-info/WHEEL
vedro_pw-0.4.0.dist-info/top_level.txt
vedro_pw-0.4.0.dist-info/RECORD
