Metadata-Version: 2.4
Name: vedro-pw
Version: 0.4.0
Summary: Integrates Playwright for automated browser testing  with customizable configuration options
Home-page: https://github.com/vedro-universe/vedro-pw
Author: Nikita Tsvetkov
Author-email: tsv1@fastmail.com
License: Apache-2.0
Project-URL: Docs, https://github.com/vedro-universe/vedro-pw
Project-URL: GitHub, https://github.com/vedro-universe/vedro-pw
Classifier: License :: OSI Approved :: Apache Software License
Classifier: Programming Language :: Python :: 3.9
Classifier: Programming Language :: Python :: 3.10
Classifier: Programming Language :: Python :: 3.11
Classifier: Programming Language :: Python :: 3.12
Classifier: Programming Language :: Python :: 3.13
Classifier: Typing :: Typed
Requires-Python: >=3.9
License-File: LICENSE
Requires-Dist: vedro<2.0,>=1.15
Requires-Dist: playwright<2.0,>=1.38
Requires-Dist: vedro-shared-resource<1.0,>=0.2
Dynamic: author
Dynamic: author-email
Dynamic: classifier
Dynamic: description
Dynamic: description-content-type
Dynamic: home-page
Dynamic: license
Dynamic: license-file
Dynamic: project-url
Dynamic: requires-dist
Dynamic: requires-python
Dynamic: summary
